tsfast/__init__.py
tsfast/_modidx.py
tsfast/basics.py
tsfast/benchmark.py
tsfast/quaternions.py
tsfast/spectogram.py
tsfast/tune.py
tsfast/data/__init__.py
tsfast/data/block.py
tsfast/data/core.py
tsfast/data/loader.py
tsfast/data/split.py
tsfast/data/transforms.py
tsfast/datasets/__init__.py
tsfast/datasets/benchmark.py
tsfast/datasets/core.py
tsfast/inference/__init__.py
tsfast/inference/core.py
tsfast/learner/__init__.py
tsfast/learner/callbacks.py
tsfast/learner/losses.py
tsfast/models/__init__.py
tsfast/models/cnn.py
tsfast/models/layers.py
tsfast/models/rnn.py
tsfast/pinn/__init__.py
tsfast/pinn/core.py
tsfast/prediction/__init__.py
tsfast/prediction/ar.py
tsfast/prediction/core.py
tsfast/prediction/fransys.py
tsfast-0.1.8.dist-info/licenses/LICENSE
tsfast-0.1.8.dist-info/METADATA
tsfast-0.1.8.dist-info/WHEEL
tsfast-0.1.8.dist-info/entry_points.txt
tsfast-0.1.8.dist-info/top_level.txt
tsfast-0.1.8.dist-info/RECORD
