Metadata-Version: 2.4
Name: tsfast
Version: 0.1.8
Summary: A description of your project
Home-page: https://github.com/daniel-om-weber/tsfast
Author: Daniel Oliver Martin Weber
Author-email: daniel.om.weber@gmail.com
License: Apache Software License 2.0
Keywords: fastai time-series system-identification deep-learning pytorch fransys
Classifier: Development Status :: 3 - Alpha
Classifier: Intended Audience :: Developers
Classifier: Natural Language :: English
Classifier: Programming Language :: Python :: 3.10
Classifier: Programming Language :: Python :: 3.11
Classifier: Programming Language :: Python :: 3.12
Classifier: License :: OSI Approved :: Apache Software License
Requires-Python: >=3.10
License-File: LICENSE
Requires-Dist: fastai>=2.7.0
Requires-Dist: torch>=2.1
Requires-Dist: identibench
Requires-Dist: matplotlib
Requires-Dist: nbdev>2
Requires-Dist: ray[tune]
Provides-Extra: dev
Requires-Dist: matplotlib; extra == "dev"
Requires-Dist: ipykernel; extra == "dev"
Requires-Dist: twine; extra == "dev"
Dynamic: author
Dynamic: author-email
Dynamic: classifier
Dynamic: description
Dynamic: description-content-type
Dynamic: home-page
Dynamic: keywords
Dynamic: license
Dynamic: license-file
Dynamic: provides-extra
Dynamic: requires-dist
Dynamic: requires-python
Dynamic: summary
